fab_classic-1.20.1.dist-info/licenses/LICENSE
fabric/__init__.py
fabric/__main__.py
fabric/api.py
fabric/auth.py
fabric/colors.py
fabric/context_managers.py
fabric/decorators.py
fabric/docs.py
fabric/exceptions.py
fabric/io.py
fabric/job_queue.py
fabric/main.py
fabric/network.py
fabric/operations.py
fabric/sftp.py
fabric/state.py
fabric/task_utils.py
fabric/tasks.py
fabric/thread_handling.py
fabric/utils.py
fabric/version.py
fabric/contrib/__init__.py
fabric/contrib/console.py
fabric/contrib/django.py
fabric/contrib/files.py
fabric/contrib/project.py
fab_classic-1.20.1.dist-info/METADATA
fab_classic-1.20.1.dist-info/WHEEL
fab_classic-1.20.1.dist-info/entry_points.txt
fab_classic-1.20.1.dist-info/top_level.txt
fab_classic-1.20.1.dist-info/RECORD
