Metadata-Version: 2.4
Name: fab-classic
Version: 1.20.1
Summary: fab-classic is a simple, Pythonic tool for remote execution and deployment.
Home-page: https://github.com/ploxiln/fab-classic
Author: Jeff Forcier
Author-email: jeff@bitprophet.org
Maintainer: Pierce Lopez
Maintainer-email: pierce.lopez@gmail.com
Classifier: Development Status :: 5 - Production/Stable
Classifier: Environment :: Console
Classifier: Intended Audience :: Developers
Classifier: Intended Audience :: System Administrators
Classifier: License :: OSI Approved :: BSD License
Classifier: Operating System :: MacOS :: MacOS X
Classifier: Operating System :: POSIX
Classifier: Operating System :: Unix
Classifier: Programming Language :: Python :: 3
Classifier: Topic :: Software Development :: Build Tools
Classifier: Topic :: Software Development :: Libraries :: Python Modules
Classifier: Topic :: System :: Clustering
Classifier: Topic :: System :: Systems Administration
Requires-Python: >=3.5
License-File: LICENSE
Requires-Dist: paramiko-ng>=2.0
Dynamic: author
Dynamic: author-email
Dynamic: classifier
Dynamic: description
Dynamic: home-page
Dynamic: license-file
Dynamic: maintainer
Dynamic: maintainer-email
Dynamic: requires-dist
Dynamic: requires-python
Dynamic: summary
